{
  "name": "card",
  "homepage": "https://github.com/jessepollak/card",
  "authors": [
    "Jesse Pollak <jpollak92@gmail.com>"
  ],
  "description": "Card let's you add an interactive, CSS3 credit card animation to your credit card form to help your users through the process.",
  "main": [
    "dist/card.js"
  ],
  "keywords": [
    "card",
    "credit",
    "card",
    "form"
  ],
  "dependencies": {
    "jquery": ">=1.5"
  },
  "license": "MIT",
  "ignore": [
    "**/.*",
    "node_modules",
    "example",
    "test",
    "tests"
  ],
  "version": "2.2.1",
  "_release": "2.2.1",
  "_resolution": {
    "type": "version",
    "tag": "v2.2.1",
    "commit": "e2dfaa23ed912999e61c9cfdddd33a83c8e9c645"
  },
  "_source": "https://github.com/jessepollak/card.git",
  "_target": "^2.0.3",
  "_originalSource": "card"
}